{
  "7.0": {
    "changes": "https://jira.mongodb.org/issues/?jql=project%20%3D%20SERVER%20AND%20fixVersion%20%3D%20%227.0.32%22%20ORDER%20BY%20status%20DESC%2C%20priority%20DESC",
    "date": "04/13/2026",
    "eol": "2027-08-31",
    "githash": "40a2e0f542b0a68f0ed51fa216e9d38b9917fe14",
    "linux": "ubuntu2204",
    "notes": "https://docs.mongodb.org/master/release-notes/7.0/",
    "pgp": [
      {
        "fingerprints": [
          "E58830201F7DD82CD808AA84160D26BB1785BA38"
        ],
        "url": "https://pgp.mongodb.com/server-7.0.asc"
      }
    ],
    "targets": {
      "debian11": {
        "arches": [
          "amd64"
        ],
        "image": "debian:bullseye-slim",
        "suite": "bullseye"
      },
      "debian12": {
        "arches": [
          "amd64"
        ],
        "image": "debian:bookworm-slim",
        "suite": "bookworm"
      },
      "ubuntu2004": {
        "arches": [
          "amd64",
          "arm64v8"
        ],
        "image": "ubuntu:focal",
        "suite": "focal"
      },
      "ubuntu2204": {
        "arches": [
          "amd64",
          "arm64v8"
        ],
        "image": "ubuntu:jammy",
        "suite": "jammy"
      },
      "windows": {
        "arches": [
          "amd64"
        ],
        "features": [
          "MiscellaneousTools",
          "Router",
          "ServerNoService"
        ],
        "msi": "https://fastdl.mongodb.org/windows/mongodb-windows-x86_64-7.0.32-signed.msi",
        "sha256": "02bb67e1e490b4dc587d853b7ce30197f798c15faba5d48aadf4891bba695072",
        "variants": [
          "windowsservercore-ltsc2025",
          "windowsservercore-ltsc2022",
          "nanoserver-ltsc2022"
        ]
      }
    },
    "version": "7.0.32"
  },
  "7.0-rc": null,
  "8.0": {
    "changes": "https://jira.mongodb.org/issues/?jql=project%20%3D%20SERVER%20AND%20fixVersion%20%3D%20%228.0.21%22%20ORDER%20BY%20status%20DESC%2C%20priority%20DESC",
    "date": "04/08/2026",
    "eol": "2029-10-31",
    "githash": "e67138ffda9f90b59531128bc43678bb5ad105ed",
    "linux": "ubuntu2404",
    "notes": "https://docs.mongodb.org/master/release-notes/8.0/",
    "pgp": [
      {
        "fingerprints": [
          "4B0752C1BCA238C0B4EE14DC41DE058A4E7DCA05"
        ],
        "url": "https://pgp.mongodb.com/server-8.0.asc"
      }
    ],
    "targets": {
      "debian12": {
        "arches": [
          "amd64"
        ],
        "image": "debian:bookworm-slim",
        "suite": "bookworm"
      },
      "ubuntu2004": {
        "arches": [
          "amd64",
          "arm64v8"
        ],
        "image": "ubuntu:focal",
        "suite": "focal"
      },
      "ubuntu2204": {
        "arches": [
          "amd64",
          "arm64v8"
        ],
        "image": "ubuntu:jammy",
        "suite": "jammy"
      },
      "ubuntu2404": {
        "arches": [
          "amd64",
          "arm64v8"
        ],
        "image": "ubuntu:noble",
        "suite": "noble"
      },
      "windows": {
        "arches": [
          "amd64"
        ],
        "features": [
          "MiscellaneousTools",
          "Router",
          "ServerNoService"
        ],
        "msi": "https://fastdl.mongodb.org/windows/mongodb-windows-x86_64-8.0.21-signed.msi",
        "sha256": "b107b121c75025be9df72c421127c581c5d3e7a5e6a52c0c057fe37227ad035b",
        "variants": [
          "windowsservercore-ltsc2025",
          "windowsservercore-ltsc2022",
          "nanoserver-ltsc2022"
        ]
      }
    },
    "version": "8.0.21"
  },
  "8.0-rc": {
    "changes": "https://jira.mongodb.org/issues/?jql=project%20%3D%20SERVER%20AND%20fixVersion%20%3D%20%228.0.21%22%20ORDER%20BY%20status%20DESC%2C%20priority%20DESC",
    "date": "04/02/2026",
    "eol": "2029-10-31",
    "githash": "e67138ffda9f90b59531128bc43678bb5ad105ed",
    "linux": "ubuntu2404",
    "notes": "https://docs.mongodb.org/master/release-notes/8.0/",
    "pgp": [
      {
        "fingerprints": [
          "28DE23AF08040FB24C33F36381B0EBBBADCEA95C"
        ],
        "url": "https://pgp.mongodb.com/server-dev.asc"
      },
      {
        "fingerprints": [
          "4B0752C1BCA238C0B4EE14DC41DE058A4E7DCA05"
        ],
        "url": "https://pgp.mongodb.com/server-8.0.asc"
      }
    ],
    "targets": {
      "debian12": {
        "arches": [
          "amd64"
        ],
        "image": "debian:bookworm-slim",
        "suite": "bookworm"
      },
      "ubuntu2004": {
        "arches": [
          "amd64",
          "arm64v8"
        ],
        "image": "ubuntu:focal",
        "suite": "focal"
      },
      "ubuntu2204": {
        "arches": [
          "amd64",
          "arm64v8"
        ],
        "image": "ubuntu:jammy",
        "suite": "jammy"
      },
      "ubuntu2404": {
        "arches": [
          "amd64",
          "arm64v8"
        ],
        "image": "ubuntu:noble",
        "suite": "noble"
      },
      "windows": {
        "arches": [
          "amd64"
        ],
        "features": [
          "MiscellaneousTools",
          "Router",
          "ServerNoService"
        ],
        "msi": "https://fastdl.mongodb.org/windows/mongodb-windows-x86_64-8.0.21-rc1-signed.msi",
        "sha256": "281946de0d1105f14284f7276d861be52cbb6284a3998916f158867ed0cd9620",
        "variants": [
          "windowsservercore-ltsc2025",
          "windowsservercore-ltsc2022",
          "nanoserver-ltsc2022"
        ]
      }
    },
    "version": "8.0.21-rc1"
  },
  "8.2": {
    "changes": "https://jira.mongodb.org/issues/?jql=project%20%3D%20SERVER%20AND%20fixVersion%20%3D%20%228.2.7%22%20ORDER%20BY%20status%20DESC%2C%20priority%20DESC",
    "date": "03/30/2026",
    "eol": "2026-07-31",
    "githash": "8f6785264a643d2eeb5e4046f7876a23e40e1a09",
    "linux": "ubuntu2404",
    "notes": "https://docs.mongodb.org/master/release-notes/8.2/",
    "pgp": [
      {
        "fingerprints": [
          "4B0752C1BCA238C0B4EE14DC41DE058A4E7DCA05"
        ],
        "url": "https://pgp.mongodb.com/server-8.0.asc"
      }
    ],
    "targets": {
      "debian12": {
        "arches": [
          "amd64"
        ],
        "image": "debian:bookworm-slim",
        "suite": "bookworm"
      },
      "ubuntu2004": {
        "arches": [
          "amd64",
          "arm64v8"
        ],
        "image": "ubuntu:focal",
        "suite": "focal"
      },
      "ubuntu2204": {
        "arches": [
          "amd64",
          "arm64v8"
        ],
        "image": "ubuntu:jammy",
        "suite": "jammy"
      },
      "ubuntu2404": {
        "arches": [
          "amd64",
          "arm64v8"
        ],
        "image": "ubuntu:noble",
        "suite": "noble"
      },
      "windows": {
        "arches": [
          "amd64"
        ],
        "features": [
          "MiscellaneousTools",
          "Router",
          "ServerNoService"
        ],
        "msi": "https://fastdl.mongodb.org/windows/mongodb-windows-x86_64-8.2.7-signed.msi",
        "sha256": "6a326fa3ea7f2013ef28247ea4e68faddaeffc5f19cabed1059e23488986379b",
        "variants": [
          "windowsservercore-ltsc2025",
          "windowsservercore-ltsc2022",
          "nanoserver-ltsc2022"
        ]
      }
    },
    "version": "8.2.7"
  },
  "8.2-rc": null,
  "8.3": null,
  "8.3-rc": {
    "changes": "https://jira.mongodb.org/issues/?jql=project%20%3D%20SERVER%20AND%20fixVersion%20%3D%20%228.3.0-rc5%22%20ORDER%20BY%20status%20DESC%2C%20priority%20DESC",
    "date": "04/06/2026",
    "dockerNeedsVersion": "8.2",
    "eol": null,
    "githash": "f5af85fa793dbcd9962aa559bcb17adb1627bc6c",
    "linux": "ubuntu2404",
    "notes": "https://docs.mongodb.org/master/release-notes/8.3/",
    "pgp": [
      {
        "fingerprints": [
          "28DE23AF08040FB24C33F36381B0EBBBADCEA95C"
        ],
        "url": "https://pgp.mongodb.com/server-dev.asc"
      },
      {
        "fingerprints": [
          "4B0752C1BCA238C0B4EE14DC41DE058A4E7DCA05"
        ],
        "url": "https://pgp.mongodb.com/server-8.0.asc"
      }
    ],
    "targets": {
      "debian12": {
        "arches": [
          "amd64"
        ],
        "image": "debian:bookworm-slim",
        "suite": "bookworm"
      },
      "ubuntu2004": {
        "arches": [
          "amd64",
          "arm64v8"
        ],
        "image": "ubuntu:focal",
        "suite": "focal"
      },
      "ubuntu2204": {
        "arches": [
          "amd64",
          "arm64v8"
        ],
        "image": "ubuntu:jammy",
        "suite": "jammy"
      },
      "ubuntu2404": {
        "arches": [
          "amd64",
          "arm64v8"
        ],
        "image": "ubuntu:noble",
        "suite": "noble"
      },
      "windows": {
        "arches": [
          "amd64"
        ],
        "features": [
          "MiscellaneousTools",
          "Router",
          "ServerNoService"
        ],
        "msi": "https://fastdl.mongodb.org/windows/mongodb-windows-x86_64-8.3.0-rc5-signed.msi",
        "sha256": "94aaf3b1eb02d695ade45fce0d253d93340091988a4173cb8823f08a3cf88b10",
        "variants": [
          "windowsservercore-ltsc2025",
          "windowsservercore-ltsc2022",
          "nanoserver-ltsc2022"
        ]
      }
    },
    "version": "8.3.0-rc5"
  }
}
